caputils.py
caputils-1.1.dist-info/LICENSE
caputils-1.1.dist-info/METADATA
caputils-1.1.dist-info/WHEEL
caputils-1.1.dist-info/top_level.txt
caputils-1.1.dist-info/RECORD
