Metadata-Version: 2.1
Name: caputils
Version: 1.1
Summary: Simple utilities for pcap parsing and wrappers for commands bundled with Wireshark.
Author: chillb0nes
License: MIT License
Project-URL: repository, https://github.com/chillb0nes/caputils
Classifier: Topic :: Software Development :: Libraries :: Python Modules
Classifier: Operating System :: OS Independent
Classifier: License :: OSI Approved :: MIT License
Classifier: Programming Language :: Python :: 3.8
Classifier: Programming Language :: Python :: 3.9
Classifier: Programming Language :: Python :: 3.10
Classifier: Programming Language :: Python :: 3.11
Requires-Python: >=3.8
License-File: LICENSE
Requires-Dist: dpkt ~=1.9.8
